{
  "name": "SubTopic",
  "fields": [
    {
      "fieldName": "name",
      "fieldType": "String",
      "fieldValidateRules": ["required", "unique"]
    }
  ],
  "relationships": [
    {
      "relationshipName": "statements",
      "otherEntityName": "statement",
      "relationshipType": "many-to-many",
      "ownerSide": false,
      "otherEntityRelationshipName": "subTopics"
    }
  ],
  "changelogDate": "20201021125822",
  "entityTableName": "sub_topic",
  "dto": "no",
  "pagination": "no",
  "service": "serviceClass",
  "jpaMetamodelFiltering": false,
  "fluentMethods": true,
  "readOnly": false,
  "embedded": false,
  "clientRootFolder": "",
  "applications": "*",
  "searchEngine": "elasticsearch",
  "databaseType": "sql"
}
